{
  "characteristics_list": [
    {
      "run": {
        "REAL_ENV_CK_CAFFE_BATCH_SIZE": "", 
        "REAL_ENV_CK_CAFFE_ITERATIONS": "", 
        "REAL_ENV_CK_CAFFE_MODEL": "", 
        "execution_time": 0.0, 
        "execution_time_with_module": 24.172675848007202, 
        "per_layer_info": [
          {
            "direction": "forward", 
            "index": 0, 
            "label": "00: data", 
            "time_ms": 0.488494, 
            "time_s": 0.000488494
          }, 
          {
            "direction": "backward", 
            "index": 0, 
            "label": "00: data", 
            "time_ms": 0.0, 
            "time_s": 0.0
          }, 
          {
            "direction": "forward", 
            "index": 1, 
            "label": "01: conv1", 
            "time_ms": 61.1872, 
            "time_s": 0.0611872
          }, 
          {
            "direction": "backward", 
            "index": 1, 
            "label": "01: conv1", 
            "time_ms": 0.0, 
            "time_s": 0.0
          }, 
          {
            "direction": "forward", 
            "index": 2, 
            "label": "02: relu1", 
            "time_ms": 2.18063, 
            "time_s": 0.00218063
          }, 
          {
            "direction": "backward", 
            "index": 2, 
            "label": "02: relu1", 
            "time_ms": 0.0, 
            "time_s": 0.0
          }, 
          {
            "direction": "forward", 
            "index": 3, 
            "label": "03: norm1", 
            "time_ms": 4.57184, 
            "time_s": 0.00457184
          }, 
          {
            "direction": "backward", 
            "index": 3, 
            "label": "03: norm1", 
            "time_ms": 0.0, 
            "time_s": 0.0
          }, 
          {
            "direction": "forward", 
            "index": 4, 
            "label": "04: pool1", 
            "time_ms": 3.04629, 
            "time_s": 0.00304629
          }, 
          {
            "direction": "backward", 
            "index": 4, 
            "label": "04: pool1", 
            "time_ms": 0.0, 
            "time_s": 0.0
          }, 
          {
            "direction": "forward", 
            "index": 5, 
            "label": "05: conv2", 
            "time_ms": 102.029, 
            "time_s": 0.102029
          }, 
          {
            "direction": "backward", 
            "index": 5, 
            "label": "05: conv2", 
            "time_ms": 0.0, 
            "time_s": 0.0
          }, 
          {
            "direction": "forward", 
            "index": 6, 
            "label": "06: relu2", 
            "time_ms": 1.72416, 
            "time_s": 0.00172416
          }, 
          {
            "direction": "backward", 
            "index": 6, 
            "label": "06: relu2", 
            "time_ms": 0.0, 
            "time_s": 0.0
          }, 
          {
            "direction": "forward", 
            "index": 7, 
            "label": "07: norm2", 
            "time_ms": 3.36821, 
            "time_s": 0.00336821
          }, 
          {
            "direction": "backward", 
            "index": 7, 
            "label": "07: norm2", 
            "time_ms": 0.0, 
            "time_s": 0.0
          }, 
          {
            "direction": "forward", 
            "index": 8, 
            "label": "08: pool2", 
            "time_ms": 2.2212, 
            "time_s": 0.0022212
          }, 
          {
            "direction": "backward", 
            "index": 8, 
            "label": "08: pool2", 
            "time_ms": 0.0, 
            "time_s": 0.0
          }, 
          {
            "direction": "forward", 
            "index": 9, 
            "label": "09: conv3", 
            "time_ms": 59.3275, 
            "time_s": 0.059327500000000005
          }, 
          {
            "direction": "backward", 
            "index": 9, 
            "label": "09: conv3", 
            "time_ms": 0.0, 
            "time_s": 0.0
          }, 
          {
            "direction": "forward", 
            "index": 10, 
            "label": "10: relu3", 
            "time_ms": 1.20165, 
            "time_s": 0.00120165
          }, 
          {
            "direction": "backward", 
            "index": 10, 
            "label": "10: relu3", 
            "time_ms": 0.0, 
            "time_s": 0.0
          }, 
          {
            "direction": "forward", 
            "index": 11, 
            "label": "11: conv4", 
            "time_ms": 62.5606, 
            "time_s": 0.06256060000000001
          }, 
          {
            "direction": "backward", 
            "index": 11, 
            "label": "11: conv4", 
            "time_ms": 0.0, 
            "time_s": 0.0
          }, 
          {
            "direction": "forward", 
            "index": 12, 
            "label": "12: relu4", 
            "time_ms": 1.19911, 
            "time_s": 0.00119911
          }, 
          {
            "direction": "backward", 
            "index": 12, 
            "label": "12: relu4", 
            "time_ms": 0.0, 
            "time_s": 0.0
          }, 
          {
            "direction": "forward", 
            "index": 13, 
            "label": "13: conv5", 
            "time_ms": 56.3875, 
            "time_s": 0.05638750000000001
          }, 
          {
            "direction": "backward", 
            "index": 13, 
            "label": "13: conv5", 
            "time_ms": 0.0, 
            "time_s": 0.0
          }, 
          {
            "direction": "forward", 
            "index": 14, 
            "label": "14: relu5", 
            "time_ms": 1.11113, 
            "time_s": 0.0011111299999999999
          }, 
          {
            "direction": "backward", 
            "index": 14, 
            "label": "14: relu5", 
            "time_ms": 0.0, 
            "time_s": 0.0
          }, 
          {
            "direction": "forward", 
            "index": 15, 
            "label": "15: pool5", 
            "time_ms": 1.21233, 
            "time_s": 0.00121233
          }, 
          {
            "direction": "backward", 
            "index": 15, 
            "label": "15: pool5", 
            "time_ms": 0.0, 
            "time_s": 0.0
          }, 
          {
            "direction": "forward", 
            "index": 16, 
            "label": "16: fc6", 
            "time_ms": 1796.29, 
            "time_s": 1.79629
          }, 
          {
            "direction": "backward", 
            "index": 16, 
            "label": "16: fc6", 
            "time_ms": 0.0, 
            "time_s": 0.0
          }, 
          {
            "direction": "forward", 
            "index": 17, 
            "label": "17: relu6", 
            "time_ms": 0.942831, 
            "time_s": 0.000942831
          }, 
          {
            "direction": "backward", 
            "index": 17, 
            "label": "17: relu6", 
            "time_ms": 0.0, 
            "time_s": 0.0
          }, 
          {
            "direction": "forward", 
            "index": 18, 
            "label": "18: drop6", 
            "time_ms": 84.8295, 
            "time_s": 0.0848295
          }, 
          {
            "direction": "backward", 
            "index": 18, 
            "label": "18: drop6", 
            "time_ms": 0.0, 
            "time_s": 0.0
          }, 
          {
            "direction": "forward", 
            "index": 19, 
            "label": "19: fc7", 
            "time_ms": 442.771, 
            "time_s": 0.442771
          }, 
          {
            "direction": "backward", 
            "index": 19, 
            "label": "19: fc7", 
            "time_ms": 0.0, 
            "time_s": 0.0
          }, 
          {
            "direction": "forward", 
            "index": 20, 
            "label": "20: relu7", 
            "time_ms": 0.932368, 
            "time_s": 0.000932368
          }, 
          {
            "direction": "backward", 
            "index": 20, 
            "label": "20: relu7", 
            "time_ms": 0.0, 
            "time_s": 0.0
          }, 
          {
            "direction": "forward", 
            "index": 21, 
            "label": "21: drop7", 
            "time_ms": 1.23436, 
            "time_s": 0.0012343599999999999
          }, 
          {
            "direction": "backward", 
            "index": 21, 
            "label": "21: drop7", 
            "time_ms": 0.0, 
            "time_s": 0.0
          }, 
          {
            "direction": "forward", 
            "index": 22, 
            "label": "22: fc8", 
            "time_ms": 93.1321, 
            "time_s": 0.0931321
          }, 
          {
            "direction": "backward", 
            "index": 22, 
            "label": "22: fc8", 
            "time_ms": 0.0, 
            "time_s": 0.0
          }, 
          {
            "direction": "forward", 
            "index": 23, 
            "label": "23: prob", 
            "time_ms": 3.4474, 
            "time_s": 0.0034474
          }, 
          {
            "direction": "backward", 
            "index": 23, 
            "label": "23: prob", 
            "time_ms": 0.0, 
            "time_s": 0.0
          }
        ], 
        "post_processed": "yes", 
        "repeat": 1, 
        "return_code": 0, 
        "run_success": "yes", 
        "run_success_bool": true, 
        "time_bw_ms": 0.0, 
        "time_bw_s": 0.0, 
        "time_fw_ms": 2797.65, 
        "time_fw_s": 2.79765, 
        "time_fwbw_ms": 2801.61, 
        "time_fwbw_s": 2.80161, 
        "time_total_ms": 2801.61, 
        "time_total_ms_kernel_0": 2801.61, 
        "time_total_s": 2.80161, 
        "time_total_s_kernel_0": 2.80161, 
        "total_execution_time": 0.0
      }
    }, 
    {
      "run": {
        "REAL_ENV_CK_CAFFE_BATCH_SIZE": "", 
        "REAL_ENV_CK_CAFFE_ITERATIONS": "", 
        "REAL_ENV_CK_CAFFE_MODEL": "", 
        "execution_time": 0.0, 
        "execution_time_with_module": 23.797497034072876, 
        "per_layer_info": [
          {
            "direction": "forward", 
            "index": 0, 
            "label": "00: data", 
            "time_ms": 0.493568, 
            "time_s": 0.000493568
          }, 
          {
            "direction": "backward", 
            "index": 0, 
            "label": "00: data", 
            "time_ms": 0.0, 
            "time_s": 0.0
          }, 
          {
            "direction": "forward", 
            "index": 1, 
            "label": "01: conv1", 
            "time_ms": 61.5289, 
            "time_s": 0.061528900000000004
          }, 
          {
            "direction": "backward", 
            "index": 1, 
            "label": "01: conv1", 
            "time_ms": 0.0, 
            "time_s": 0.0
          }, 
          {
            "direction": "forward", 
            "index": 2, 
            "label": "02: relu1", 
            "time_ms": 2.2151, 
            "time_s": 0.0022151000000000002
          }, 
          {
            "direction": "backward", 
            "index": 2, 
            "label": "02: relu1", 
            "time_ms": 0.0, 
            "time_s": 0.0
          }, 
          {
            "direction": "forward", 
            "index": 3, 
            "label": "03: norm1", 
            "time_ms": 4.70429, 
            "time_s": 0.004704290000000001
          }, 
          {
            "direction": "backward", 
            "index": 3, 
            "label": "03: norm1", 
            "time_ms": 0.0, 
            "time_s": 0.0
          }, 
          {
            "direction": "forward", 
            "index": 4, 
            "label": "04: pool1", 
            "time_ms": 3.07455, 
            "time_s": 0.00307455
          }, 
          {
            "direction": "backward", 
            "index": 4, 
            "label": "04: pool1", 
            "time_ms": 0.0, 
            "time_s": 0.0
          }, 
          {
            "direction": "forward", 
            "index": 5, 
            "label": "05: conv2", 
            "time_ms": 100.106, 
            "time_s": 0.100106
          }, 
          {
            "direction": "backward", 
            "index": 5, 
            "label": "05: conv2", 
            "time_ms": 0.0, 
            "time_s": 0.0
          }, 
          {
            "direction": "forward", 
            "index": 6, 
            "label": "06: relu2", 
            "time_ms": 1.6903, 
            "time_s": 0.0016903
          }, 
          {
            "direction": "backward", 
            "index": 6, 
            "label": "06: relu2", 
            "time_ms": 0.0, 
            "time_s": 0.0
          }, 
          {
            "direction": "forward", 
            "index": 7, 
            "label": "07: norm2", 
            "time_ms": 3.41202, 
            "time_s": 0.00341202
          }, 
          {
            "direction": "backward", 
            "index": 7, 
            "label": "07: norm2", 
            "time_ms": 0.0, 
            "time_s": 0.0
          }, 
          {
            "direction": "forward", 
            "index": 8, 
            "label": "08: pool2", 
            "time_ms": 2.20871, 
            "time_s": 0.00220871
          }, 
          {
            "direction": "backward", 
            "index": 8, 
            "label": "08: pool2", 
            "time_ms": 0.0, 
            "time_s": 0.0
          }, 
          {
            "direction": "forward", 
            "index": 9, 
            "label": "09: conv3", 
            "time_ms": 61.1734, 
            "time_s": 0.0611734
          }, 
          {
            "direction": "backward", 
            "index": 9, 
            "label": "09: conv3", 
            "time_ms": 0.0, 
            "time_s": 0.0
          }, 
          {
            "direction": "forward", 
            "index": 10, 
            "label": "10: relu3", 
            "time_ms": 1.19765, 
            "time_s": 0.0011976500000000002
          }, 
          {
            "direction": "backward", 
            "index": 10, 
            "label": "10: relu3", 
            "time_ms": 0.0, 
            "time_s": 0.0
          }, 
          {
            "direction": "forward", 
            "index": 11, 
            "label": "11: conv4", 
            "time_ms": 64.2017, 
            "time_s": 0.0642017
          }, 
          {
            "direction": "backward", 
            "index": 11, 
            "label": "11: conv4", 
            "time_ms": 0.0, 
            "time_s": 0.0
          }, 
          {
            "direction": "forward", 
            "index": 12, 
            "label": "12: relu4", 
            "time_ms": 1.15468, 
            "time_s": 0.00115468
          }, 
          {
            "direction": "backward", 
            "index": 12, 
            "label": "12: relu4", 
            "time_ms": 0.0, 
            "time_s": 0.0
          }, 
          {
            "direction": "forward", 
            "index": 13, 
            "label": "13: conv5", 
            "time_ms": 56.2436, 
            "time_s": 0.056243600000000005
          }, 
          {
            "direction": "backward", 
            "index": 13, 
            "label": "13: conv5", 
            "time_ms": 0.0, 
            "time_s": 0.0
          }, 
          {
            "direction": "forward", 
            "index": 14, 
            "label": "14: relu5", 
            "time_ms": 1.11435, 
            "time_s": 0.00111435
          }, 
          {
            "direction": "backward", 
            "index": 14, 
            "label": "14: relu5", 
            "time_ms": 0.0, 
            "time_s": 0.0
          }, 
          {
            "direction": "forward", 
            "index": 15, 
            "label": "15: pool5", 
            "time_ms": 1.19519, 
            "time_s": 0.00119519
          }, 
          {
            "direction": "backward", 
            "index": 15, 
            "label": "15: pool5", 
            "time_ms": 0.0, 
            "time_s": 0.0
          }, 
          {
            "direction": "forward", 
            "index": 16, 
            "label": "16: fc6", 
            "time_ms": 1195.16, 
            "time_s": 1.19516
          }, 
          {
            "direction": "backward", 
            "index": 16, 
            "label": "16: fc6", 
            "time_ms": 0.0, 
            "time_s": 0.0
          }, 
          {
            "direction": "forward", 
            "index": 17, 
            "label": "17: relu6", 
            "time_ms": 0.993931, 
            "time_s": 0.000993931
          }, 
          {
            "direction": "backward", 
            "index": 17, 
            "label": "17: relu6", 
            "time_ms": 0.0, 
            "time_s": 0.0
          }, 
          {
            "direction": "forward", 
            "index": 18, 
            "label": "18: drop6", 
            "time_ms": 1.53923, 
            "time_s": 0.0015392300000000002
          }, 
          {
            "direction": "backward", 
            "index": 18, 
            "label": "18: drop6", 
            "time_ms": 0.0, 
            "time_s": 0.0
          }, 
          {
            "direction": "forward", 
            "index": 19, 
            "label": "19: fc7", 
            "time_ms": 456.039, 
            "time_s": 0.45603899999999997
          }, 
          {
            "direction": "backward", 
            "index": 19, 
            "label": "19: fc7", 
            "time_ms": 0.0, 
            "time_s": 0.0
          }, 
          {
            "direction": "forward", 
            "index": 20, 
            "label": "20: relu7", 
            "time_ms": 0.982875, 
            "time_s": 0.000982875
          }, 
          {
            "direction": "backward", 
            "index": 20, 
            "label": "20: relu7", 
            "time_ms": 0.0, 
            "time_s": 0.0
          }, 
          {
            "direction": "forward", 
            "index": 21, 
            "label": "21: drop7", 
            "time_ms": 1.27632, 
            "time_s": 0.0012763199999999998
          }, 
          {
            "direction": "backward", 
            "index": 21, 
            "label": "21: drop7", 
            "time_ms": 0.0, 
            "time_s": 0.0
          }, 
          {
            "direction": "forward", 
            "index": 22, 
            "label": "22: fc8", 
            "time_ms": 92.5033, 
            "time_s": 0.0925033
          }, 
          {
            "direction": "backward", 
            "index": 22, 
            "label": "22: fc8", 
            "time_ms": 0.0, 
            "time_s": 0.0
          }, 
          {
            "direction": "forward", 
            "index": 23, 
            "label": "23: prob", 
            "time_ms": 3.41987, 
            "time_s": 0.00341987
          }, 
          {
            "direction": "backward", 
            "index": 23, 
            "label": "23: prob", 
            "time_ms": 0.0, 
            "time_s": 0.0
          }
        ], 
        "post_processed": "yes", 
        "repeat": 1, 
        "return_code": 0, 
        "run_success": "yes", 
        "run_success_bool": true, 
        "time_bw_ms": 0.0, 
        "time_bw_s": 0.0, 
        "time_fw_ms": 2127.75, 
        "time_fw_s": 2.1277500000000003, 
        "time_fwbw_ms": 2142.17, 
        "time_fwbw_s": 2.14217, 
        "time_total_ms": 2142.17, 
        "time_total_ms_kernel_0": 2142.17, 
        "time_total_s": 2.14217, 
        "time_total_s_kernel_0": 2.14217, 
        "total_execution_time": 0.0
      }
    }, 
    {
      "run": {
        "REAL_ENV_CK_CAFFE_BATCH_SIZE": "", 
        "REAL_ENV_CK_CAFFE_ITERATIONS": "", 
        "REAL_ENV_CK_CAFFE_MODEL": "", 
        "execution_time": 0.0, 
        "execution_time_with_module": 23.057631969451904, 
        "per_layer_info": [
          {
            "direction": "forward", 
            "index": 0, 
            "label": "00: data", 
            "time_ms": 0.489034, 
            "time_s": 0.0004890340000000001
          }, 
          {
            "direction": "backward", 
            "index": 0, 
            "label": "00: data", 
            "time_ms": 0.0, 
            "time_s": 0.0
          }, 
          {
            "direction": "forward", 
            "index": 1, 
            "label": "01: conv1", 
            "time_ms": 61.2832, 
            "time_s": 0.0612832
          }, 
          {
            "direction": "backward", 
            "index": 1, 
            "label": "01: conv1", 
            "time_ms": 0.0, 
            "time_s": 0.0
          }, 
          {
            "direction": "forward", 
            "index": 2, 
            "label": "02: relu1", 
            "time_ms": 2.12642, 
            "time_s": 0.00212642
          }, 
          {
            "direction": "backward", 
            "index": 2, 
            "label": "02: relu1", 
            "time_ms": 0.0, 
            "time_s": 0.0
          }, 
          {
            "direction": "forward", 
            "index": 3, 
            "label": "03: norm1", 
            "time_ms": 4.55333, 
            "time_s": 0.00455333
          }, 
          {
            "direction": "backward", 
            "index": 3, 
            "label": "03: norm1", 
            "time_ms": 0.0, 
            "time_s": 0.0
          }, 
          {
            "direction": "forward", 
            "index": 4, 
            "label": "04: pool1", 
            "time_ms": 3.04299, 
            "time_s": 0.00304299
          }, 
          {
            "direction": "backward", 
            "index": 4, 
            "label": "04: pool1", 
            "time_ms": 0.0, 
            "time_s": 0.0
          }, 
          {
            "direction": "forward", 
            "index": 5, 
            "label": "05: conv2", 
            "time_ms": 100.979, 
            "time_s": 0.100979
          }, 
          {
            "direction": "backward", 
            "index": 5, 
            "label": "05: conv2", 
            "time_ms": 0.0, 
            "time_s": 0.0
          }, 
          {
            "direction": "forward", 
            "index": 6, 
            "label": "06: relu2", 
            "time_ms": 1.69093, 
            "time_s": 0.00169093
          }, 
          {
            "direction": "backward", 
            "index": 6, 
            "label": "06: relu2", 
            "time_ms": 0.0, 
            "time_s": 0.0
          }, 
          {
            "direction": "forward", 
            "index": 7, 
            "label": "07: norm2", 
            "time_ms": 3.41432, 
            "time_s": 0.00341432
          }, 
          {
            "direction": "backward", 
            "index": 7, 
            "label": "07: norm2", 
            "time_ms": 0.0, 
            "time_s": 0.0
          }, 
          {
            "direction": "forward", 
            "index": 8, 
            "label": "08: pool2", 
            "time_ms": 2.23966, 
            "time_s": 0.00223966
          }, 
          {
            "direction": "backward", 
            "index": 8, 
            "label": "08: pool2", 
            "time_ms": 0.0, 
            "time_s": 0.0
          }, 
          {
            "direction": "forward", 
            "index": 9, 
            "label": "09: conv3", 
            "time_ms": 63.8049, 
            "time_s": 0.06380490000000001
          }, 
          {
            "direction": "backward", 
            "index": 9, 
            "label": "09: conv3", 
            "time_ms": 0.0, 
            "time_s": 0.0
          }, 
          {
            "direction": "forward", 
            "index": 10, 
            "label": "10: relu3", 
            "time_ms": 1.20598, 
            "time_s": 0.0012059800000000002
          }, 
          {
            "direction": "backward", 
            "index": 10, 
            "label": "10: relu3", 
            "time_ms": 0.0, 
            "time_s": 0.0
          }, 
          {
            "direction": "forward", 
            "index": 11, 
            "label": "11: conv4", 
            "time_ms": 65.029, 
            "time_s": 0.065029
          }, 
          {
            "direction": "backward", 
            "index": 11, 
            "label": "11: conv4", 
            "time_ms": 0.0, 
            "time_s": 0.0
          }, 
          {
            "direction": "forward", 
            "index": 12, 
            "label": "12: relu4", 
            "time_ms": 1.23362, 
            "time_s": 0.00123362
          }, 
          {
            "direction": "backward", 
            "index": 12, 
            "label": "12: relu4", 
            "time_ms": 0.0, 
            "time_s": 0.0
          }, 
          {
            "direction": "forward", 
            "index": 13, 
            "label": "13: conv5", 
            "time_ms": 58.086, 
            "time_s": 0.058086
          }, 
          {
            "direction": "backward", 
            "index": 13, 
            "label": "13: conv5", 
            "time_ms": 0.0, 
            "time_s": 0.0
          }, 
          {
            "direction": "forward", 
            "index": 14, 
            "label": "14: relu5", 
            "time_ms": 1.17863, 
            "time_s": 0.0011786300000000002
          }, 
          {
            "direction": "backward", 
            "index": 14, 
            "label": "14: relu5", 
            "time_ms": 0.0, 
            "time_s": 0.0
          }, 
          {
            "direction": "forward", 
            "index": 15, 
            "label": "15: pool5", 
            "time_ms": 1.2105, 
            "time_s": 0.0012105
          }, 
          {
            "direction": "backward", 
            "index": 15, 
            "label": "15: pool5", 
            "time_ms": 0.0, 
            "time_s": 0.0
          }, 
          {
            "direction": "forward", 
            "index": 16, 
            "label": "16: fc6", 
            "time_ms": 1165.73, 
            "time_s": 1.16573
          }, 
          {
            "direction": "backward", 
            "index": 16, 
            "label": "16: fc6", 
            "time_ms": 0.0, 
            "time_s": 0.0
          }, 
          {
            "direction": "forward", 
            "index": 17, 
            "label": "17: relu6", 
            "time_ms": 0.9695, 
            "time_s": 0.0009695000000000001
          }, 
          {
            "direction": "backward", 
            "index": 17, 
            "label": "17: relu6", 
            "time_ms": 0.0, 
            "time_s": 0.0
          }, 
          {
            "direction": "forward", 
            "index": 18, 
            "label": "18: drop6", 
            "time_ms": 1.52655, 
            "time_s": 0.00152655
          }, 
          {
            "direction": "backward", 
            "index": 18, 
            "label": "18: drop6", 
            "time_ms": 0.0, 
            "time_s": 0.0
          }, 
          {
            "direction": "forward", 
            "index": 19, 
            "label": "19: fc7", 
            "time_ms": 449.816, 
            "time_s": 0.449816
          }, 
          {
            "direction": "backward", 
            "index": 19, 
            "label": "19: fc7", 
            "time_ms": 0.0, 
            "time_s": 0.0
          }, 
          {
            "direction": "forward", 
            "index": 20, 
            "label": "20: relu7", 
            "time_ms": 0.931544, 
            "time_s": 0.0009315440000000001
          }, 
          {
            "direction": "backward", 
            "index": 20, 
            "label": "20: relu7", 
            "time_ms": 0.0, 
            "time_s": 0.0
          }, 
          {
            "direction": "forward", 
            "index": 21, 
            "label": "21: drop7", 
            "time_ms": 1.43811, 
            "time_s": 0.00143811
          }, 
          {
            "direction": "backward", 
            "index": 21, 
            "label": "21: drop7", 
            "time_ms": 0.0, 
            "time_s": 0.0
          }, 
          {
            "direction": "forward", 
            "index": 22, 
            "label": "22: fc8", 
            "time_ms": 93.2169, 
            "time_s": 0.09321689999999999
          }, 
          {
            "direction": "backward", 
            "index": 22, 
            "label": "22: fc8", 
            "time_ms": 0.0, 
            "time_s": 0.0
          }, 
          {
            "direction": "forward", 
            "index": 23, 
            "label": "23: prob", 
            "time_ms": 3.22255, 
            "time_s": 0.0032225500000000002
          }, 
          {
            "direction": "backward", 
            "index": 23, 
            "label": "23: prob", 
            "time_ms": 0.0, 
            "time_s": 0.0
          }
        ], 
        "post_processed": "yes", 
        "repeat": 1, 
        "return_code": 0, 
        "run_success": "yes", 
        "run_success_bool": true, 
        "time_bw_ms": 0.0, 
        "time_bw_s": 0.0, 
        "time_fw_ms": 2098.55, 
        "time_fw_s": 2.0985500000000004, 
        "time_fwbw_ms": 2125.85, 
        "time_fwbw_s": 2.12585, 
        "time_total_ms": 2125.85, 
        "time_total_ms_kernel_0": 2125.85, 
        "time_total_s": 2.12585, 
        "time_total_s_kernel_0": 2.12585, 
        "total_execution_time": 0.0
      }
    }
  ], 
  "choices": {
    "cmd_key": "time_gpu", 
    "compile_only_once": "yes", 
    "compile_type": "dynamic", 
    "compiler_flags": {}, 
    "compiler_vars": {}, 
    "cpu_freq": "max", 
    "data_uoa": "caffe", 
    "dataset_file": "", 
    "device_id": "", 
    "energy": "no", 
    "env": {
      "CK_CAFFE_BATCH_SIZE": 2, 
      "CK_CAFFE_GPU_ID": 0, 
      "CK_CAFFE_ITERATIONS": 50, 
      "CK_CAFFE_MODEL": "/home/anton/CK/ck-caffe/program/caffe/tmp/tmp-2VOKcE.prototxt", 
      "CK_CPU_FREQUENCY": "max", 
      "CK_GPU_FREQUENCY": "max"
    }, 
    "gpu_freq": "max", 
    "host_os": "linux-32", 
    "module_uoa": "b0ac08fe1d3c2615", 
    "no_state_check": "yes", 
    "repeat": 1, 
    "skip_calibration": "yes", 
    "target_os": "linux-32", 
    "target_os_bits": "32"
  }, 
  "choices_order": [
    "##env#CK_CAFFE_BATCH_SIZE"
  ], 
  "features": {
    "compiler_version": {
      "list": [], 
      "raw": "", 
      "str": ""
    }, 
    "number_of_selected_compiler_flags": 0, 
    "platform": {
      "cpu": {
        "all_freqs": {
          "0": [
            1900000, 
            1800000, 
            1700000, 
            1600000, 
            1500000, 
            1400000, 
            1300000, 
            1200000, 
            1100000, 
            1000000, 
            900000, 
            800000, 
            700000, 
            650000, 
            600000, 
            550000, 
            500000, 
            450000, 
            400000, 
            350000, 
            300000
          ], 
          "1": [
            1900000, 
            1800000, 
            1700000, 
            1600000, 
            1500000, 
            1400000, 
            1300000, 
            1200000, 
            1100000, 
            1000000, 
            900000, 
            800000, 
            700000, 
            650000, 
            600000, 
            550000, 
            500000, 
            450000, 
            400000, 
            350000, 
            300000
          ], 
          "2": [
            1900000, 
            1800000, 
            1700000, 
            1600000, 
            1500000, 
            1400000, 
            1300000, 
            1200000, 
            1100000, 
            1000000, 
            900000, 
            800000, 
            700000, 
            650000, 
            600000, 
            550000, 
            500000, 
            450000, 
            400000, 
            350000, 
            300000
          ], 
          "3": [
            1900000, 
            1800000, 
            1700000, 
            1600000, 
            1500000, 
            1400000, 
            1300000, 
            1200000, 
            1100000, 
            1000000, 
            900000, 
            800000, 
            700000, 
            650000, 
            600000, 
            550000, 
            500000, 
            450000, 
            400000, 
            350000, 
            300000
          ]
        }, 
        "cpu_abi": "", 
        "cpu_features": "swp half thumb fastmult vfp edsp thumbee neon vfpv3 tls vfpv4 idiva idivt", 
        "current_freq": {
          "0": 1900.0, 
          "1": 1900.0, 
          "2": 1900.0, 
          "3": 1900.0
        }, 
        "max_freq": {
          "0": 1900.0, 
          "1": 1900.0, 
          "2": 1900.0, 
          "3": 1900.0
        }, 
        "name": "SAMSUNG EXYNOS5 (Flattened Device Tree)", 
        "num_proc": "4", 
        "sub_name": "ARMv7 Processor rev 3 (v7l)"
      }, 
      "cpu_misc": {
        "0": {
          "BogoMIPS": "48.00", 
          "CPU architecture": "7", 
          "CPU implementer": "0x41", 
          "CPU part": "0xc0f", 
          "CPU revision": "3", 
          "CPU variant": "0x2", 
          "Features": "swp half thumb fastmult vfp edsp thumbee neon vfpv3 tls vfpv4 idiva idivt", 
          "all_freqs": [
            "0", 
            "0", 
            "0", 
            "0", 
            "0", 
            "0", 
            "0", 
            "0", 
            "0", 
            "0", 
            "0", 
            "0", 
            "0", 
            "0", 
            "0", 
            "0", 
            "0", 
            "0", 
            "0", 
            "0", 
            "0"
          ], 
          "ck_cpu_name": "ARMv7 Processor rev 3 (v7l)", 
          "ck_cpu_subname": "ARMv7 Processor rev 3 (v7l)", 
          "cpu_features": "swp half thumb fastmult vfp edsp thumbee neon vfpv3 tls vfpv4 idiva idivt", 
          "cur_freq": 1900.0, 
          "max_freq": 1900.0, 
          "model name": "ARMv7 Processor rev 3 (v7l)", 
          "processor": "0"
        }, 
        "1": {
          "BogoMIPS": "50.66", 
          "CPU architecture": "7", 
          "CPU implementer": "0x41", 
          "CPU part": "0xc0f", 
          "CPU revision": "3", 
          "CPU variant": "0x2", 
          "Features": "swp half thumb fastmult vfp edsp thumbee neon vfpv3 tls vfpv4 idiva idivt", 
          "all_freqs": [
            "1", 
            "1", 
            "1", 
            "1", 
            "1", 
            "1", 
            "1", 
            "1", 
            "1", 
            "1", 
            "1", 
            "1", 
            "1", 
            "1", 
            "1", 
            "1", 
            "1", 
            "1", 
            "1", 
            "1", 
            "1"
          ], 
          "ck_cpu_name": "ARMv7 Processor rev 3 (v7l)", 
          "ck_cpu_subname": "ARMv7 Processor rev 3 (v7l)", 
          "cpu_features": "swp half thumb fastmult vfp edsp thumbee neon vfpv3 tls vfpv4 idiva idivt", 
          "cur_freq": 1900.0, 
          "max_freq": 1900.0, 
          "model name": "ARMv7 Processor rev 3 (v7l)", 
          "processor": "1"
        }, 
        "2": {
          "BogoMIPS": "50.66", 
          "CPU architecture": "7", 
          "CPU implementer": "0x41", 
          "CPU part": "0xc0f", 
          "CPU revision": "3", 
          "CPU variant": "0x2", 
          "Features": "swp half thumb fastmult vfp edsp thumbee neon vfpv3 tls vfpv4 idiva idivt", 
          "all_freqs": [
            "2", 
            "2", 
            "2", 
            "2", 
            "2", 
            "2", 
            "2", 
            "2", 
            "2", 
            "2", 
            "2", 
            "2", 
            "2", 
            "2", 
            "2", 
            "2", 
            "2", 
            "2", 
            "2", 
            "2", 
            "2"
          ], 
          "ck_cpu_name": "ARMv7 Processor rev 3 (v7l)", 
          "ck_cpu_subname": "ARMv7 Processor rev 3 (v7l)", 
          "cpu_features": "swp half thumb fastmult vfp edsp thumbee neon vfpv3 tls vfpv4 idiva idivt", 
          "cur_freq": 1900.0, 
          "max_freq": 1900.0, 
          "model name": "ARMv7 Processor rev 3 (v7l)", 
          "processor": "2"
        }, 
        "3": {
          "BogoMIPS": "50.66", 
          "CPU architecture": "7", 
          "CPU implementer": "0x41", 
          "CPU part": "0xc0f", 
          "CPU revision": "3", 
          "CPU variant": "0x2", 
          "Features": "swp half thumb fastmult vfp edsp thumbee neon vfpv3 tls vfpv4 idiva idivt", 
          "Hardware": "SAMSUNG EXYNOS5 (Flattened Device Tree)", 
          "Revision": "0000", 
          "Serial": "0000000000000000", 
          "all_freqs": [
            "3", 
            "3", 
            "3", 
            "3", 
            "3", 
            "3", 
            "3", 
            "3", 
            "3", 
            "3", 
            "3", 
            "3", 
            "3", 
            "3", 
            "3", 
            "3", 
            "3", 
            "3", 
            "3", 
            "3", 
            "3"
          ], 
          "ck_cpu_name": "SAMSUNG EXYNOS5 (Flattened Device Tree)", 
          "ck_cpu_subname": "ARMv7 Processor rev 3 (v7l)", 
          "cpu_features": "swp half thumb fastmult vfp edsp thumbee neon vfpv3 tls vfpv4 idiva idivt", 
          "cur_freq": 1900.0, 
          "max_freq": 1900.0, 
          "model name": "ARMv7 Processor rev 3 (v7l)", 
          "processor": "3"
        }
      }, 
      "cpu_new_format": "", 
      "cpu_unique": [
        {
          "BogoMIPS": "48.00", 
          "CPU architecture": "7", 
          "CPU implementer": "0x41", 
          "CPU part": "0xc0f", 
          "CPU revision": "3", 
          "CPU variant": "0x2", 
          "Features": "swp half thumb fastmult vfp edsp thumbee neon vfpv3 tls vfpv4 idiva idivt", 
          "all_freqs": [
            "0", 
            "0", 
            "0", 
            "0", 
            "0", 
            "0", 
            "0", 
            "0", 
            "0", 
            "0", 
            "0", 
            "0", 
            "0", 
            "0", 
            "0", 
            "0", 
            "0", 
            "0", 
            "0", 
            "0", 
            "0"
          ], 
          "ck_cpu_name": "ARMv7 Processor rev 3 (v7l)", 
          "ck_cpu_subname": "ARMv7 Processor rev 3 (v7l)", 
          "cpu_features": "swp half thumb fastmult vfp edsp thumbee neon vfpv3 tls vfpv4 idiva idivt", 
          "cur_freq": 1900.0, 
          "max_freq": 1900.0, 
          "model name": "ARMv7 Processor rev 3 (v7l)", 
          "processor": "0"
        }, 
        {
          "BogoMIPS": "50.66", 
          "CPU architecture": "7", 
          "CPU implementer": "0x41", 
          "CPU part": "0xc0f", 
          "CPU revision": "3", 
          "CPU variant": "0x2", 
          "Features": "swp half thumb fastmult vfp edsp thumbee neon vfpv3 tls vfpv4 idiva idivt", 
          "Hardware": "SAMSUNG EXYNOS5 (Flattened Device Tree)", 
          "Revision": "0000", 
          "Serial": "0000000000000000", 
          "all_freqs": [
            "3", 
            "3", 
            "3", 
            "3", 
            "3", 
            "3", 
            "3", 
            "3", 
            "3", 
            "3", 
            "3", 
            "3", 
            "3", 
            "3", 
            "3", 
            "3", 
            "3", 
            "3", 
            "3", 
            "3", 
            "3"
          ], 
          "ck_cpu_name": "SAMSUNG EXYNOS5 (Flattened Device Tree)", 
          "ck_cpu_subname": "ARMv7 Processor rev 3 (v7l)", 
          "cpu_features": "swp half thumb fastmult vfp edsp thumbee neon vfpv3 tls vfpv4 idiva idivt", 
          "cur_freq": 1900.0, 
          "max_freq": 1900.0, 
          "model name": "ARMv7 Processor rev 3 (v7l)", 
          "processor": "3"
        }
      ], 
      "gpu": {
        "all_freqs": [
          "100000000", 
          "177000000", 
          "266000000", 
          "350000000", 
          "420000000", 
          "480000000", 
          "533000000", 
          "600000000"
        ], 
        "current_freq": "600000000", 
        "name": "", 
        "vendor": ""
      }, 
      "gpu_misc": {}, 
      "os": {
        "bits": "32", 
        "ck_os_base_uoa": "", 
        "ck_os_uoa": "linux-32", 
        "name": "Linux 3.8.11", 
        "name_long": "Linux-3.8.11-armv7l-ARMv7_Processor_rev_3_-v7l-with-gentoo-2.2", 
        "name_short": "Linux 3.8.11"
      }, 
      "os_misc": {}, 
      "platform": {
        "model": "", 
        "name": "", 
        "vendor": ""
      }, 
      "platform_misc": {}
    }, 
    "statistical_repetitions": 3
  }
}
